RECLAC/RECLAC.py
RECLAC/__init__.py
RECLAC/boxcount.py
RECLAC/recurrence_plot.py
RECLAC-1.0.0.dist-info/LICENSE
RECLAC-1.0.0.dist-info/METADATA
RECLAC-1.0.0.dist-info/WHEEL
RECLAC-1.0.0.dist-info/top_level.txt
RECLAC-1.0.0.dist-info/RECORD
