Metadata-Version: 2.1
Name: RECLAC
Version: 1.0.0
Summary: A package to compute recurrence lacunarity and other box-counting-based recurrence quantifiers
Home-page: https://github.com/ToBraun/RECLAC
Author: Tobias Braun
Author-email: tobraun@pik-potsdam.de
License: UNKNOWN
Platform: UNKNOWN
Classifier: Programming Language :: Python :: 3.7
Classifier: License :: OSI Approved :: MIT License
Requires-Dist: numpy (>=1.21)
Requires-Dist: scipy (>=1.2.1)
